MLTT/__init__.py
MLTT/cache.py
MLTT/data_split.py
MLTT/utils.py
MLTT/allocation/__init__.py
MLTT/allocation/allocators.py
MLTT/allocation/backend.py
MLTT/allocation/backtesting.py
MLTT/alphas/__init__.py
MLTT/alphas/alpha.py
MLTT/alphas/base.py
MLTT/alphas/data.py
MLTT/alphas/functions.py
MLTT/alphas/generation.py
MLTT/alphas/operations.py
MLTT/alphas/performance.py
MLTT/alphas/visualization.py
MLTT/data_loading/__init__.py
MLTT/data_loading/defillama.py
MLTT/data_loading/dumper.py
MLTT/data_loading/formatter.py
MLTT/data_loading/interface.py
MLTT/data_loading/selection.py
MLTT/models/__init__.py
MLTT/models/basic.py
MLTT/models/cointegration.py
MLTT/models/common.py
MLTT/models/estimation.py
MLTT/models/fancy_regression.py
MLTT/models/kalman.py
MLTT/models/mean_reversion.py
MLTT/models/momentum.py
MLTT/models/price_models.py
MLTT/options/__init__.py
MLTT/options/pricers.py
MLTT/orderbook/__init__.py
MLTT/orderbook/features.py
MLTT/orderbook/features.pyi
MLTT/orderbook/preprocessing.py
MLTT/report/__init__.py
MLTT/report/metrics.py
MLTT/report/report.py
MLTT/technical/__init__.py
MLTT/technical/features.py
MLTT/technical/non_trivial.py
MLTT/technical/support_resistance.py
MLTT/validation/__init__.py
MLTT/validation/buckets.py
MLTT/validation/insample_overfit.py
MLTT/validation/leak_check.py
MLTT/validation/walkforward.py
mltt-1.19.7.dist-info/licenses/LICENSE
mltt-1.19.7.dist-info/METADATA
mltt-1.19.7.dist-info/WHEEL
mltt-1.19.7.dist-info/top_level.txt
mltt-1.19.7.dist-info/RECORD
